modoboa_stats/__init__.py
modoboa_stats/apps.py
modoboa_stats/forms.py
modoboa_stats/graphics.py
modoboa_stats/handlers.py
modoboa_stats/lib.py
modoboa_stats/modo_extension.py
modoboa_stats/signals.py
modoboa_stats/urls.py
modoboa_stats/views.py
modoboa_stats/locale/cs_CZ/LC_MESSAGES/django.mo
modoboa_stats/locale/cs_CZ/LC_MESSAGES/django.po
modoboa_stats/locale/cs_CZ/LC_MESSAGES/djangojs.mo
modoboa_stats/locale/cs_CZ/LC_MESSAGES/djangojs.po
modoboa_stats/locale/de/LC_MESSAGES/django.mo
modoboa_stats/locale/de/LC_MESSAGES/django.po
modoboa_stats/locale/de/LC_MESSAGES/djangojs.mo
modoboa_stats/locale/de/LC_MESSAGES/djangojs.po
modoboa_stats/locale/el_GR/LC_MESSAGES/django.mo
modoboa_stats/locale/el_GR/LC_MESSAGES/django.po
modoboa_stats/locale/el_GR/LC_MESSAGES/djangojs.mo
modoboa_stats/locale/el_GR/LC_MESSAGES/djangojs.po
modoboa_stats/locale/en/LC_MESSAGES/django.mo
modoboa_stats/locale/en/LC_MESSAGES/django.po
modoboa_stats/locale/en/LC_MESSAGES/djangojs.mo
modoboa_stats/locale/en/LC_MESSAGES/djangojs.po
modoboa_stats/locale/es/LC_MESSAGES/django.mo
modoboa_stats/locale/es/LC_MESSAGES/django.po
modoboa_stats/locale/es/LC_MESSAGES/djangojs.mo
modoboa_stats/locale/es/LC_MESSAGES/djangojs.po
modoboa_stats/locale/fr/LC_MESSAGES/django.mo
modoboa_stats/locale/fr/LC_MESSAGES/django.po
modoboa_stats/locale/fr/LC_MESSAGES/djangojs.mo
modoboa_stats/locale/fr/LC_MESSAGES/djangojs.po
modoboa_stats/locale/it/LC_MESSAGES/django.mo
modoboa_stats/locale/it/LC_MESSAGES/django.po
modoboa_stats/locale/it/LC_MESSAGES/djangojs.mo
modoboa_stats/locale/it/LC_MESSAGES/djangojs.po
modoboa_stats/locale/ja_JP/LC_MESSAGES/django.mo
modoboa_stats/locale/ja_JP/LC_MESSAGES/django.po
modoboa_stats/locale/ja_JP/LC_MESSAGES/djangojs.mo
modoboa_stats/locale/ja_JP/LC_MESSAGES/djangojs.po
modoboa_stats/locale/nl_NL/LC_MESSAGES/django.mo
modoboa_stats/locale/nl_NL/LC_MESSAGES/django.po
modoboa_stats/locale/nl_NL/LC_MESSAGES/djangojs.mo
modoboa_stats/locale/nl_NL/LC_MESSAGES/djangojs.po
modoboa_stats-1.5.0.dist-info/LICENSE
modoboa_stats-1.5.0.dist-info/METADATA
modoboa_stats-1.5.0.dist-info/WHEEL
modoboa_stats-1.5.0.dist-info/top_level.txt
modoboa_stats-1.5.0.dist-info/RECORD
